{
	"node:normal": {
		"hash": "656d5e45cf0ea4e95c3f532bcc7d07815174da8a2323e471ea7696bd7a609f70",
		"hashEntries": "APIFY_VERSION=3.4.2;CRAWLEE_VERSION=3.13.9;NODE_VERSION=18,20,22,24"
	},
	"node:playwright": {
		"hash": "d91c18e56b85c3952d985b5025546cfac1edff493e2b357f2f92ca452e7866e9",
		"hashEntries": "APIFY_VERSION=3.4.2;CAMOUFOX_VERSION=0.4.1;CRAWLEE_VERSION=3.13.8;NODE_VERSION=18,20,22,24;PLAYWRIGHT_VERSION=1.51.0,1.51.1,1.52.0,1.53.0,1.53.1"
	},
	"node:puppeteer-chrome": {
		"hash": "dcc69584be53efef54e828980a5c4d53522f230677ad8d0ce5b03029216eaa0d",
		"hashEntries": "APIFY_VERSION=3.4.2;CRAWLEE_VERSION=3.13.8;NODE_VERSION=18,20,22,24;PUPPETEER_VERSION=24.8.2,24.9.0,24.10.0,24.10.1,24.10.2"
	},
	"python:normal": {
		"hash": "083dd556248b889130c81faab1641ecaa87276a0eda4416f981ce9359011d013",
		"hashEntries": "APIFY_VERSION=2.6.0;PYTHON_VERSION=3.9,3.10,3.11,3.12,3.13"
	},
	"python:playwright": {
		"hash": "d1ae2b3caf89d73a032d080e8fd897aa3ca5aabd7dba781b5dced6f04adfe709",
		"hashEntries": "APIFY_VERSION=2.6.0;PLAYWRIGHT_VERSION=1.49.1,1.50.0,1.51.0,1.52.0,1.53.0;PYTHON_VERSION=3.9,3.10,3.11,3.12,3.13"
	},
	"python:selenium": {
		"hash": "9245011db1cf15764f883946d0279e32ab4e1231b940dcb8daac0c60b6b4b8a6",
		"hashEntries": "APIFY_VERSION=2.6.0;PYTHON_VERSION=3.9,3.10,3.11,3.12,3.13;SELENIUM_VERSION=4.29.0,4.30.0,4.31.0,4.32.0,4.33.0"
	}
}
