{
	"node:normal": {
		"hash": "adea5c4cafed9f35f1763f93c29ffec55b9e5ce5341a4956443fe67d2853f904",
		"hashEntries": "APIFY_VERSION=3.4.2;CRAWLEE_VERSION=3.13.8-beta.9;NODE_VERSION=18,20,22,24"
	},
	"node:playwright": {
		"hash": "af0e4bd98ed4990cbb676ad87db25da146adc87298831246476763feb43c9429",
		"hashEntries": "APIFY_VERSION=3.4.2;CAMOUFOX_VERSION=0.4.0;CRAWLEE_VERSION=3.13.8-beta.9;NODE_VERSION=18,20,22,24;PLAYWRIGHT_VERSION=1.50.1,1.51.0,1.51.1,1.52.0,1.53.0"
	},
	"node:puppeteer-chrome": {
		"hash": "b413267aab53f64d3fb946097efb8e125b4fb1484d7c2aa8c8476283f8659353",
		"hashEntries": "APIFY_VERSION=3.4.2;CRAWLEE_VERSION=3.13.8-beta.8;NODE_VERSION=18,20,22,24;PUPPETEER_VERSION=24.8.0,24.8.1,24.8.2,24.9.0,24.10.0"
	},
	"python:normal": {
		"hash": "1cb2878266be74fa177026f8cfecd2a91e21646df264441ca2ef0571c1837a9e",
		"hashEntries": "APIFY_VERSION=2.2.1;PYTHON_VERSION=3.9,3.10,3.11,3.12,3.13"
	},
	"python:playwright": {
		"hash": "f1568eff432c27be9af509dacc11f7daa70881c7f8e0e53b5c01cf392ccfe5e1",
		"hashEntries": "APIFY_VERSION=2.2.1;PLAYWRIGHT_VERSION=1.47.0,1.48.0,1.49.0,1.49.1,1.50.0;PYTHON_VERSION=3.9,3.10,3.11,3.12,3.13"
	},
	"python:selenium": {
		"hash": "c6474bc43d1960f1d2867c774278e9d38dfdadda7070d42edc3c839043d8df20",
		"hashEntries": "APIFY_VERSION=2.2.1;PYTHON_VERSION=3.9,3.10,3.11,3.12,3.13;SELENIUM_VERSION=4.26.1,4.27.0,4.27.1,4.28.0,4.28.1"
	}
}
